compiledb/__init__.py
compiledb/__main__.py
compiledb/__version__.py
compiledb/cli.py
compiledb/compiler.py
compiledb/parser.py
compiledb/utils.py
compiledb/commands/__init__.py
compiledb/commands/make.py
compiledbd-0.9.1.dist-info/LICENSE
compiledbd-0.9.1.dist-info/METADATA
compiledbd-0.9.1.dist-info/WHEEL
compiledbd-0.9.1.dist-info/entry_points.txt
compiledbd-0.9.1.dist-info/top_level.txt
compiledbd-0.9.1.dist-info/RECORD
